certbot_dns_ownadmin/__init__.py
certbot_dns_ownadmin/dns_ownadmin.py
certbot_dns_ownadmin-1.0.5.dist-info/METADATA
certbot_dns_ownadmin-1.0.5.dist-info/WHEEL
certbot_dns_ownadmin-1.0.5.dist-info/entry_points.txt
certbot_dns_ownadmin-1.0.5.dist-info/top_level.txt
certbot_dns_ownadmin-1.0.5.dist-info/RECORD
