Metadata-Version: 2.4
Name: certbot-dns-ownadmin
Version: 1.0.5
Summary: OwnAdmin Authenticator plugin for Certbot
Home-page: https://github.com/Chudeusz/certbot-dns-powerdns-ownadmin
Author: Chudeusz
Author-email: chudeusz@ownadmin.pl
License: Apache License 2.0
Classifier: Development Status :: 5 - Production/Stable
Classifier: Environment :: Plugins
Classifier: Intended Audience :: System Administrators
Classifier: License :: OSI Approved :: Apache Software License
Classifier: Operating System :: POSIX :: Linux
Classifier: Programming Language :: Python
Classifier: Programming Language :: Python :: 3
Classifier: Programming Language :: Python :: 3.7
Classifier: Programming Language :: Python :: 3.8
Classifier: Programming Language :: Python :: 3.9
Classifier: Programming Language :: Python :: 3.10
Classifier: Programming Language :: Python :: 3.11
Classifier: Programming Language :: Python :: 3.12
Classifier: Topic :: Internet :: WWW/HTTP
Classifier: Topic :: Security
Classifier: Topic :: System :: Installation/Setup
Classifier: Topic :: System :: Networking
Classifier: Topic :: System :: Systems Administration
Classifier: Topic :: Utilities
Requires-Python: >=3.7
Requires-Dist: acme>=1.12.0
Requires-Dist: certbot>=1.12.0
Requires-Dist: dns-lexicon>=3.10.0
Requires-Dist: dnspython>=2.0
Requires-Dist: setuptools>=40.8.0
Requires-Dist: zope.interface>=5.0
Requires-Dist: requests>=2.25.0
Dynamic: author
Dynamic: author-email
Dynamic: classifier
Dynamic: description
Dynamic: description-content-type
Dynamic: home-page
Dynamic: license
Dynamic: requires-dist
Dynamic: requires-python
Dynamic: summary
